f3dasm_optimize/__init__.py
f3dasm_optimize/__version__.py
f3dasm_optimize/_src/__init__.py
f3dasm_optimize/_src/_imports.py
f3dasm_optimize/_src/evosax_optimizers.py
f3dasm_optimize/_src/nevergrad_optimizers.py
f3dasm_optimize/_src/optax_optimizers.py
f3dasm_optimize/_src/optuna_optimizers.py
f3dasm_optimize/_src/adapters/__init__.py
f3dasm_optimize/_src/adapters/evosax_implementations.py
f3dasm_optimize/_src/adapters/nevergrad_implementations.py
f3dasm_optimize/_src/adapters/optax_implementations.py
f3dasm_optimize/_src/adapters/optuna_implementations.py
f3dasm_optimize-2.0.0.dist-info/METADATA
f3dasm_optimize-2.0.0.dist-info/WHEEL
f3dasm_optimize-2.0.0.dist-info/top_level.txt
f3dasm_optimize-2.0.0.dist-info/RECORD
