Metadata-Version: 2.1
Name: f3dasm_optimize
Version: 2.0.0
Summary: f3dasm_optimize: Your one line description of the package
Home-page: https://github.com/bessagroup/f3dasm_optimize
Author: Martin van der Schelling
Author-email: M.P.vanderSchelling@tudelft.nl
License: BSD-3-Clause License
Keywords: keyword1,keyword2,keyword3
Classifier: Development Status :: 5 - Production/Stable
Classifier: Intended Audience :: Science/Research
Classifier: Topic :: Scientific/Engineering
Classifier: Topic :: Scientific/Engineering :: Artificial Intelligence
Classifier: Topic :: Scientific/Engineering :: Physics
Classifier: License :: OSI Approved :: BSD License
Classifier: Natural Language :: English
Classifier: Programming Language :: Python :: 3.8
Classifier: Programming Language :: Python :: 3.9
Classifier: Programming Language :: Python :: 3.10
Classifier: Programming Language :: Python :: 3.11
Requires-Python: >=3.8
Requires-Dist: f3dasm>=2.0.0
Provides-Extra: all
Requires-Dist: nevergrad; extra == "all"
Requires-Dist: evosax; extra == "all"
Requires-Dist: optuna; extra == "all"
Requires-Dist: optax==0.1.7; extra == "all"
